hilly/__init__.py
hilly/constants.py
hilly/io.py
hilly/ski.py
hilly/utils.py
hilly-0.1.3.dist-info/LICENSE
hilly-0.1.3.dist-info/METADATA
hilly-0.1.3.dist-info/WHEEL
hilly-0.1.3.dist-info/RECORD
