Metadata-Version: 2.1
Name: hilly
Version: 0.1.3
Summary: Tools for summarizing and viewing sporty GPX traces
Home-page: https://gitlab.com/ryanmcginger/hilly
Keywords: gpx,maps,outdoors
Author: Ryan
Author-email: code+git@mcginger.net
Requires-Python: >=3.10,<3.11
Classifier: Programming Language :: Python :: 3
Classifier: Programming Language :: Python :: 3.10
Requires-Dist: folium (>=0.14.0,<0.15.0)
Requires-Dist: geopandas (>=0.12.2,<0.13.0)
Requires-Dist: gpxcsv (>=0.2.15,<0.3.0)
Requires-Dist: gpxpy (>=1.5.0,<2.0.0)
Requires-Dist: loguru (>=0.7.0,<0.8.0)
Requires-Dist: lxml (>=4.9.2,<5.0.0)
Requires-Dist: mapclassify (>=2.5.0,<3.0.0)
Requires-Dist: matplotlib (>=3.7.1,<4.0.0)
Requires-Dist: pyqt5 (>=5.15.9,<6.0.0)
Requires-Dist: rasterio (>=1.3.6,<2.0.0)
Requires-Dist: scipy (>=1.10.1,<2.0.0)
Requires-Dist: tqdm (>=4.65.0,<5.0.0)
Project-URL: Repository, https://gitlab.com/ryanmcginger/hilly
